{
  "magic": "E!vIA5L86J2I",
  "timestamp": "2022-12-22T00:54:09.444318+00:00",
  "repo": "aaronpk/oauth-direct-interaction-grant",
  "labels": [
    {
      "name": "bug",
      "description": "Something isn't working",
      "color": "d73a4a"
    },
    {
      "name": "documentation",
      "description": "Improvements or additions to documentation",
      "color": "0075ca"
    },
    {
      "name": "duplicate",
      "description": "This issue or pull request already exists",
      "color": "cfd3d7"
    },
    {
      "name": "enhancement",
      "description": "New feature or request",
      "color": "a2eeef"
    },
    {
      "name": "good first issue",
      "description": "Good for newcomers",
      "color": "7057ff"
    },
    {
      "name": "help wanted",
      "description": "Extra attention is needed",
      "color": "008672"
    },
    {
      "name": "invalid",
      "description": "This doesn't seem right",
      "color": "e4e669"
    },
    {
      "name": "question",
      "description": "Further information is requested",
      "color": "d876e3"
    },
    {
      "name": "wontfix",
      "description": "This will not be worked on",
      "color": "ffffff"
    }
  ],
  "issues": [
    {
      "number": 3,
      "id": "I_kwDOIk8Zl85Z0Tve",
      "title": "Rename `mfa_token` to `mfa_code`?",
      "url": "https://github.com/aaronpk/oauth-direct-interaction-grant/issues/3",
      "state": "OPEN",
      "author": "aaronpk",
      "authorAssociation": "OWNER",
      "assignees": [],
      "labels": [],
      "body": "The current `mfa_token` is more like an authorization code, in that it is relatively short lived, does not provide access to any resources directly, and is only used in order to obtain an access token. So maybe this should be called `mfa_code` instead?",
      "createdAt": "2022-12-21T20:37:54Z",
      "updatedAt": "2022-12-21T20:38:00Z",
      "closedAt": null,
      "comments": []
    }
  ],
  "pulls": [
    {
      "number": 1,
      "id": "PR_kwDOIk8Zl85E8PjN",
      "title": "First round of updates",
      "url": "https://github.com/aaronpk/oauth-direct-interaction-grant/pull/1",
      "state": "MERGED",
      "author": "PieterKas",
      "authorAssociation": "CONTRIBUTOR",
      "assignees": [],
      "labels": [],
      "body": "Fleshing out use cases/scenarios, link to step-up auth, security considerations",
      "createdAt": "2022-12-09T20:24:10Z",
      "updatedAt": "2022-12-09T20:30:37Z",
      "baseRepository": "aaronpk/oauth-direct-interaction-grant",
      "baseRefName": "main",
      "baseRefOid": "aaf9ac53b814f145b4567700f4982dda8a8e0d20",
      "headRepository": "PieterKas/oauth-direct-interaction-grant",
      "headRefName": "patch-1",
      "headRefOid": "2f13cb7d454a61969fbbf1e387071c27b6e614fb",
      "closedAt": "2022-12-09T20:30:37Z",
      "mergedAt": "2022-12-09T20:30:37Z",
      "mergedBy": "aaronpk",
      "mergeCommit": {
        "oid": "a1a9117ea305068adbca1aad63b6bd5ca2b4f8f1"
      },
      "comments": [],
      "reviews": []
    },
    {
      "number": 2,
      "id": "PR_kwDOIk8Zl85F48cn",
      "title": "Added diagrams, TODOs and QUESTIONS",
      "url": "https://github.com/aaronpk/oauth-direct-interaction-grant/pull/2",
      "state": "MERGED",
      "author": "PieterKas",
      "authorAssociation": "CONTRIBUTOR",
      "assignees": [],
      "labels": [],
      "body": "Added two diagrams to capture  protocol flow (one for client initiated and one for AS initiated). Added references/placeholders for FIDO (TBD on how we do that) and also added QUESTIONS (possibly not very well informed ones ;)).",
      "createdAt": "2022-12-20T17:35:22Z",
      "updatedAt": "2022-12-21T20:38:16Z",
      "baseRepository": "aaronpk/oauth-direct-interaction-grant",
      "baseRefName": "main",
      "baseRefOid": "11f37a4a9c644fdde5fe688edc4f534805f91810",
      "headRepository": "PieterKas/oauth-direct-interaction-grant",
      "headRefName": "patch-2",
      "headRefOid": "4038625d2d630a9a47c07e3397d06be2c809e8a5",
      "closedAt": "2022-12-21T20:38:15Z",
      "mergedAt": "2022-12-21T20:38:15Z",
      "mergedBy": "aaronpk",
      "mergeCommit": {
        "oid": "940346a2bcffcf5249e40bb82d7d3acf2755cb7b"
      },
      "comments": [],
      "reviews": []
    }
  ]
}